morpheuscypher/__init__.py
morpheuscypher/version.py
morpheus_cypher-0.3.2.dist-info/LICENSE.txt
morpheus_cypher-0.3.2.dist-info/METADATA
morpheus_cypher-0.3.2.dist-info/WHEEL
morpheus_cypher-0.3.2.dist-info/top_level.txt
morpheus_cypher-0.3.2.dist-info/RECORD
