Metadata-Version: 2.2
Name: morpheus-cypher
Version: 0.3.2
Summary: Retrieve secrets from Morpheus Cypher Secret Storage
Home-page: https://github.com/tryfan/python-morpheus-cypher
Author: Nick Celebic
Author-email: ncelebic@morpheusdata.com
License-File: LICENSE.txt
Requires-Dist: requests>=2.21.0
Dynamic: author
Dynamic: author-email
Dynamic: home-page
Dynamic: requires-dist
Dynamic: summary
